scute/__init__.py
scute/advancements.py
scute/biomes.py
scute/blocks.py
scute/commands.py
scute/data_types.py
scute/datasources.py
scute/dimensions.py
scute/enchantments.py
scute/function.py
scute/heightmaps.py
scute/internal/dict_to_NBT.py
scute/internal/utils.py
scute/items.py
scute/json_text.py
scute/recipes.py
scute/relations.py
scute/scoreboards.py
scute/tags.py
scute/utils.py
scutemc-0.0.8.dist-info/WHEEL
scutemc-0.0.8.dist-info/METADATA
scutemc-0.0.8.dist-info/RECORD
